MANIFEST.in
README.md
setup.py
mp_vehicle_services.egg-info/PKG-INFO
mp_vehicle_services.egg-info/SOURCES.txt
mp_vehicle_services.egg-info/dependency_links.txt
mp_vehicle_services.egg-info/top_level.txt
services/__init__.py
services/admin.py
services/forms.py
services/managers.py
services/middleware.py
services/models.py
services/querysets.py
services/service.py
services/urls.py
services/views.py
services/locale/ru/LC_MESSAGES/django.mo
services/locale/ru/LC_MESSAGES/django.po
services/locale/uk/LC_MESSAGES/django.mo
services/locale/uk/LC_MESSAGES/django.po
services/migrations/0001_initial.py
services/migrations/0002_worker.py
services/migrations/__init__.py
services/templates/services/add-service-item.html
services/templates/services/item.html
services/templates/services/manage.html
services/templates/services/print-service-items.html
services/templates/services/print-services-table.html
services/templates/services/print-services.html
services/templates/services/report.html
services/templates/services/service-items.html