Metadata-Version: 2.1
Name: mp-vehicle-services
Version: 0.0.1
Summary: Django services app
Home-page: https://github.com/pmaigutyak/mp-vehicle-services
Author: Paul Maigutyak
Author-email: pmaigutyak@gmail.com
License: MIT
Download-URL: https://github.com/pmaigutyak/mp-vehicle-services/archive/0.0.1.tar.gz
Platform: UNKNOWN
